{"size":16,"Z":{"A":{"U":{"3":{"Z":{"d":{"6":{"4":{"":80}}}}},"B":{"E":{"R":{"F":{"E":{"E":{"":150,"N":{"L":{"A":{"N":{"D":{"":100}}}}}}},"L":{"O":{"E":{"T":{"E":{"":100}}},"T":{"E":{"":73}}}}},"M":{"A":{"U":{"S":{"":170}}}}}}},"L":{"6":{"5":{"3":{"9":{"":96}}}}},"R":{"0":{"2":{"5":{"4":{"":180}}}},"1":{"2":{"3":{"4":{"5":{"":81}}},"4":{"5":{"":54}},"6":{"7":{"0":{"":84}}}},"5":{"a":{"n":{"t":{"4":{"5":{"":120}}}}}},"9":{"8":{"1":{"":53}}}},"2":{"0":{"0":{"1":{"":69}}}},"7":{"8":{"":210}},"":130}}}}}