{"size":51,"h":{"7":{"6":{"0":{"1":{"1":{"1":{"9":{"":63}}}},"2":{"1":{"1":{"9":{"":120}}}},"5":{"0":{"8":{"":55}}},"8":{"6":{"8":{"8":{"":51}}}},"b":{"k":{"9":{"3":{"":63}}}}},"1":{"2":{"3":{"8":{"9":{"":120}}},"i":{"3":{"":110}}},"3":{"6":{"2":{"6":{"":52}}}},"4":{"1":{"6":{"":75}}},"r":{"j":{"N":{"o":{"y":{"W":{"":140}}}}}}},"2":{"0":{"9":{"9":{"9":{"":87}}}},"3":{"4":{"3":{"":62}}}},"3":{"3":{"4":{"6":{"2":{"":72}}}}},"4":{"1":{"0":{"1":{"9":{"8":{"7":{"":54}}}}}},"o":{"e":{"9":{"8":{"":81}}},"o":{"":62}}},"5":{"3":{"9":{"2":{"":53}}},"4":{"3":{"2":{"1":{"":880},"":51}}},"5":{"6":{"7":{"":75}}},"k":{"b":{"":70}},"p":{"p":{"7":{"1":{"":63,"r":{"u":{"s":{"":96}}}}}}},"r":{"y":{"":130}}},"6":{"2":{"5":{"2":{"3":{"":56}}}},"b":{"y":{"4":{"8":{"":51}}}},"h":{"r":{"":84}},"t":{"y":{"":54}}},"7":{"4":{"5":{"2":{"5":{"":58}},"5":{"1":{"":58}}}},"6":{"5":{"0":{"":110}}},"7":{"7":{"e":{"":93}}},"a":{"m":{"b":{"e":{"n":{"":76}}}}}},"8":{"3":{"2":{"5":{"8":{"9":{"":89}}}}},"g":{"w":{"2":{"":110}}}},"9":{"0":{"3":{"2":{"":50}}},"4":{"a":{"b":{"":110}}}},"H":{"4":{"G":{"2":{"":68}}}},"a":{"t":{"v":{"q":{"9":{"S":{"W":{"":150}}}}}}},"f":{"4":{"2":{"":54}}},"h":{"g":{"t":{"l":{"g":{"9":{"":68}}}}},"y":{"a":{"":71}}},"k":{"m":{"9":{"8":{"":58}}}},"l":{"4":{"s":{"j":{"":130}}}},"m":{"f":{"6":{"8":{"":51,"K":{"":78}}}}},"r":{"A":{"j":{"c":{"p":{"":120}}}}},"s":{"6":{"d":{"j":{"v":{"":64}}}}},"t":{"v":{"v":{"A":{"g":{"4":{"X":{"":160}}}}}}},"w":{"7":{"v":{"m":{"r":{"2":{"v":{"":150}}}}}}},"y":{"6":{"5":{"c":{"":110}}}}}}}}