{"c.ronaldo":39000,"c.ronaldo7":8800,"c.pfyyf":3300,"c.hghbp":2000,"c.ronaldo1":1900,"c.ronaldo9":1600,"c.brown":1000,"c.ronaldo17":1000,"c.ronaldo123":670,"c.r.e.a.m.":540,"c.r.e.a.m":520,"c.ctymrf":470,"c.ronaldo07":400,"c.ctxrf":380,"c.98012":350,"c.c.c.":350,"c.liliana":300,"c.ronaldo12":300,"c.o.c.o":300,"c.morin95":290,"c.pfyyfchnbr":290,"c.s.lewis":290,"c.money":280,"c.totoche":280,"c.ronaldo0":280,"c.cmrf":270,"c.pfyf":260,"c.hhtfkbpv":250,"c.lachapelle":250,"c.ronaldo10":250,"c.vicencio.rios":250,"c.botineau":230,"c.ronaldo.":220,"c.ronald":220,"c.reaves":220,"c.lange":210,"c.grande":210,"c.giannoni":210,"c.kerdudo":210,"c.alban":200,"c.lfytkmpz":200,"c.ronaldo2":200,"c.nrby":190,"c.ronaldo09":190,"c.mazzon":190,"c.gianluca":190,"c.ronaldo.7":190,"c.camino":180,"c.c":180,"c.pbyjhl":180}