{"size":34,"x":{"s":{"v":{"1":{"2":{"3":{"":74}},"7":{"1":{"0":{"4":{"9":{"":68}}}}}},"6":{"a":{"j":{"n":{"":55}}}},"7":{"w":{"x":{"y":{"h":{"":68}}}}},"8":{"5":{"2":{"6":{"5":{"4":{"":93}}}}}},"":140,"a":{"g":{"u":{"s":{"x":{"":66}}}}},"d":{"1":{"q":{"K":{"6":{"9":{"P":{"":72}}}}}},"x":{"2":{"5":{"4":{"7":{"6":{"5":{"9":{"":65}}}}}}}}},"e":{"g":{"o":{"1":{"3":{"":58},"":71}}},"m":{"a":{"c":{"1":{"":86}}}},"n":{"1":{"2":{"3":{"5":{"4":{"":91}}}}},"x":{"":59}},"t":{"a":{"1":{"6":{"1":{"1":{"x":{"":300}}}}},"x":{"1":{"1":{"1":{"0":{"7":{"2":{"":92}}}}}}}}}},"g":{"o":{"d":{"s":{"1":{"":61}}}},"y":{"7":{"8":{"b":{"r":{"":79}}}}}},"i":{"i":{"9":{"4":{"v":{"":56}}}},"w":{"e":{"x":{"2":{"5":{"8":{"4":{"7":{"5":{"5":{"":51}}}}}}}}}}},"j":{"8":{"d":{"3":{"g":{"":55}}}}},"k":{"n":{"j":{"l":{"y":{"x":{"x":{"7":{"":58}}}}}}}},"n":{"a":{"f":{"d":{"n":{"":68}}}}},"o":{"7":{"p":{"t":{"c":{"":99}}}}},"p":{"a":{"i":{"n":{"t":{"b":{"a":{"l":{"l":{"":180}}}}}}}}},"r":{"1":{"0":{"4":{"":58}}}},"s":{"h":{"k":{"1":{"t":{"":66}}}}},"t":{"0":{"2":{"8":{"0":{"":220}}}},"6":{"7":{"b":{"s":{"":100}}}},"g":{"h":{"i":{"t":{"1":{"":53}}}}}},"u":{"e":{"s":{"t":{"1":{"":54},"":140}}}},"w":{"f":{"c":{"z":{"w":{"":130}}}}},"z":{"2":{"0":{"1":{"1":{"":73}}}}}}}}}