{"ionela":11000,"ionutz":7900,"ionut":6800,"ionel23":5400,"ionion":5300,"ionica":4800,"ionut123":2800,"ionova":2400,"ion123":2200,"ion":2100,"ionescu":1900,"ionut1":1600,"ionel":1600,"iona":1200,"ionstorm":1100,"ionizable4":1000,"ionesco":980,"ionutu":960,"ionutionut":950,"ionita":900,"ioncannon":900,"iono":890,"ionov":830,"ionionion":820,"ionian":790,"ion123123":770,"ion2001":770,"ionescu1":750,"iona123":680,"ionut1234":670,"ionutt":630,"ion05021985":620,"ioncreanga":580,"ionaiona":570,"ionina":560,"ion123456":560,"ionutz123":540,"ion12345":510,"ion1994":480,"ionut12345":480,"ionatan":480,"ione":470,"ion2000":470,"ion1234":460,"ionel123":460,"ionic":460,"ionika":440,"ion1995":430,"ionutza":430,"ionut2000":420}