{"asx45b2":8400,"asxzasxz":2400,"asxasx":2300,"asxYs33d4S":1800,"asx4521":1200,"asx123":1000,"asxz4521":730,"asx":590,"asxcfg":560,"asxz":550,"asxsV62d7B":530,"asxzas":490,"asxzdc":480,"asx123123":470,"asxat":450,"asxz1234":440,"asxzasxz00":400,"asxz12":400,"asxz123":380,"asx5gu5kl1bm":330,"asxzasxz1":330,"asx123456":260,"asxza":260,"asxxsa":240,"asxcfgbn":230,"asxzasxza":230,"asx5gu5kl1":220,"asxasxasx":220,"asxiqrpg01":220,"asxzqw12":210,"asxsv62d7b":210,"asxcvbnm":200,"asxzasxzasxz":200,"asxbxcy214":190,"asxc2468":190,"asxcvb":190,"asxaqw":190,"asxatik123":190,"asxzzxsa":180,"asx321":180,"asxz12345":170,"asxdcf":170,"asxcasxc":170,"asxf8820":160,"asxzlknm":160,"asxtorhn":160,"asxiqrpg45":150,"asxjlhax":150,"asxcdf":150,"asxrhjirfakfr":150}