{"Djljktq":1500,"Djlbntkm":500,"Djljgfl":500,"DjlzhfV12":260,"Djljghjdjl":240,"DjljktQ":230,"Djlrf1":200,"Djljktq18":190,"Djlrf40":150,"Djljgfl8":140,"Djljkfp21":140,"Djljgfl1":130,"Djljgmzyjdf":130,"Djloos2313":120,"Djlfktq":120,"Djlrf1357":110,"Djlrf222djlrf222":110,"Djljrfyfk":110,"Djljktq1":110,"Djljhjl":110,"Djljgfl98":100,"Djlom":99,"Djljktq82":99,"Djlzyjq":96,"Djl":88,"Djlbxrf90":82,"Djljktq1963":78,"Djljkfp":77,"DjlbkF":72,"Djlrff123":70,"Djlj1tq0000":69,"Djlzyjq211":67,"Djljdjxrff":67,"Djljgmzyjd":67,"Djlzhf":66,"Djllkb242":66,"Djlrf":62,"Djlbntkm442":61,"Djljdjhjn":61,"Djlucky1":60,"Djloves1":59,"Djlf6859":58,"DjlbntkmHtyj":57,"Djl2rf.Ihfn":56,"Djljktq23":55,"Djlbkf":53,"Djljxrf":52,"Djljdjhjn765":52,"Djljrfxrf":52,"Djliquid78":51}