{"size":33,"B":{"U":{"E":{"C":{"H":{"I":{"G":{"Q":{"":100}}}}},"D":{"E":{"O":{"R":{"R":{"4":{"":99}}}}}},"F":{"8":{"3":{"n":{"1":{"1":{"8":{"":51}}}}}},"F":{"E":{"L":{"2":{"5":{"0":{"1":{"1":{"0":{"5":{"2":{"L":{"E":{"F":{"F":{"E":{"U":{"B":{"":100}}}}}}}}}}}}}}},"Q":{"":110}}}}},"L":{"1":{"1":{"":96}},"L":{"A":{"":63}}},"N":{"A":{"":63,"F":{"E":{"":140},"L":{"O":{"R":{"":94}}}},"O":{"B":{"R":{"A":{"":120}}}},"S":{"":72,"U":{"E":{"R":{"T":{"E":{"":94}}}}}},"V":{"E":{"N":{"T":{"U":{"1":{"":58},"":110,"R":{"A":{"":50}}}}}},"I":{"S":{"T":{"A":{"":230}}}}}},"D":{"I":{"A":{"":230}}},"N":{"O":{"6":{"4":{"4":{"6":{"O":{"N":{"N":{"E":{"U":{"B":{"":100}}}}}}}}}}}},"O":{"1":{"":100},"":300,"S":{"":220,"A":{"":130,"I":{"R":{"E":{"S":{"":180}}}}},"D":{"I":{"A":{"S":{"":92}}}},"R":{"":100}}},"V":{"I":{"A":{"J":{"E":{"":63}}}}}},"R":{"G":{"I":{"_":{"1":{"9":{"8":{"9":{"":100}}}}}}},"O":{"B":{"E":{"R":{"T":{"":100}}}},"N":{"E":{"":82}}}},"T":{"I":{"F":{"U":{"L":{"":71}}}}},"Y":{"I":{"L":{"M":{"A":{"Z":{"":100}}}}}},"v":{"o":{"B":{"E":{"":63}}}}}}}}