{"size":42,"A":{"v":{"g":{"1":{"2":{"0":{"8":{"":53}}}},"7":{"0":{"8":{"7":{"2":{"I":{"g":{"":110}}}}}}},"W":{"o":{"a":{"P":{"8":{"5":{"9":{"":70}}}}}}},"_":{"0":{"7":{"0":{"8":{"1":{"9":{"6":{"1":{"":200}}}}}}}}},"a":{"n":{"9":{"9":{"9":{"":89}}}}},"k":{"4":{"2":{"l":{"g":{"3":{"Y":{"":340}}}}}}},"u":{"":77,"s":{"T":{"0":{"4":{"0":{"8":{"d":{"A":{"":95}}}}}},"":56},"t":{"0":{"6":{"1":{"2":{"":59}}},"8":{"":82}},"1":{"2":{"3":{"":160},"":100},"4":{"":59},"5":{"":70},"9":{"7":{"5":{"":71}},"8":{"1":{"":84},"3":{"":64}},"9":{"2":{"":190}},"":86}},"2":{"0":{"0":{"8":{"":850},"9":{"":86}},"1":{"0":{"":140},"1":{"":54},"2":{"":51}},"":140},"1":{"0":{"8":{"":170}}},"2":{"":53}},"4":{"4":{"":150}},"6":{"9":{"":53}},"8":{"9":{"5":{"0":{"7":{"6":{"4":{"8":{"2":{"3":{"9":{"":98}}}}}}}}}}},"9":{"0":{"":51},"1":{"":52}},"":1100,"a":{"2":{"2":{"8":{"6":{"7":{"":64}}}}},"":320},"i":{"n":{"":170,"a":{"":110},"o":{"v":{"i":{"c":{"h":{"a":{"":68}}}}}}}},"o":{"v":{"i":{"c":{"h":{"a":{"":74}}}}}}}}},"y":{"s":{"t":{"1":{"6":{"":61}},"":140}}}}}}}